CORBA.py
CosNaming_idl.py
PortableServer.py
PortableServer__POA.py
_omniConnMgmt.cpython-310-x86_64-linux-gnu.so
_omniConnMgmt.cpython-310-x86_64-linux-gnu.so.4
_omniConnMgmt.cpython-310-x86_64-linux-gnu.so.4.2
_omniZIOP.cpython-310-x86_64-linux-gnu.so
_omniZIOP.cpython-310-x86_64-linux-gnu.so.4
_omniZIOP.cpython-310-x86_64-linux-gnu.so.4.2
_omnicodesets.cpython-310-x86_64-linux-gnu.so
_omnicodesets.cpython-310-x86_64-linux-gnu.so.4
_omnicodesets.cpython-310-x86_64-linux-gnu.so.4.2
_omniidl.cpython-310-x86_64-linux-gnu.so
_omniidl.cpython-310-x86_64-linux-gnu.so.4
_omniidl.cpython-310-x86_64-linux-gnu.so.4.2
_omnipy.cpython-310-x86_64-linux-gnu.so
_omnipy.cpython-310-x86_64-linux-gnu.so.4
_omnipy.cpython-310-x86_64-linux-gnu.so.4.2
omniORB.pth
CosNaming/__init__.py
CosNaming__POA/__init__.py
omniORB/BiDirPolicy.py
omniORB/CORBA.py
omniORB/Compression.py
omniORB/PortableServer.py
omniORB/PortableServer__POA.py
omniORB/URI.py
omniORB/ZIOP.py
omniORB/__init__.py
omniORB/ami.py
omniORB/any.py
omniORB/boxes_idl.py
omniORB/codesets.py
omniORB/compression_idl.py
omniORB/corbaidl_idl.py
omniORB/interceptors.py
omniORB/ir_idl.py
omniORB/main.py
omniORB/messaging_idl.py
omniORB/minorCodes.py
omniORB/omniConnectionMgmt.py
omniORB/omniPolicy.py
omniORB/omniZIOP.py
omniORB/pollable_idl.py
omniORB/tcInternal.py
omniORB/ziop_idl.py
omniORB/COS/CosCollection_idl.py
omniORB/COS/CosCompoundLifeCycle_idl.py
omniORB/COS/CosContainment_idl.py
omniORB/COS/CosEventChannelAdmin_idl.py
omniORB/COS/CosEventComm_idl.py
omniORB/COS/CosExternalizationContainment_idl.py
omniORB/COS/CosExternalizationReference_idl.py
omniORB/COS/CosExternalization_idl.py
omniORB/COS/CosGraphs_idl.py
omniORB/COS/CosLifeCycleContainment_idl.py
omniORB/COS/CosLifeCycleReference_idl.py
omniORB/COS/CosLifeCycle_idl.py
omniORB/COS/CosNaming_idl.py
omniORB/COS/CosNotification_idl.py
omniORB/COS/CosNotifyChannelAdmin_idl.py
omniORB/COS/CosNotifyComm_idl.py
salome_omniorb-4.2.5.dist-info/METADATA
salome_omniorb-4.2.5.dist-info/WHEEL
salome_omniorb-4.2.5.dist-info/entry_points.txt
salome_omniorb-4.2.5.dist-info/RECORD
