Metadata-Version: 1.2
Name: salome-omniorb
Version: 4.2.5
Summary: Free CORBA ORB
Home-page: https://omniorb.sourceforge.io/
Author: Duncan Grisby
Author-email: duncan@grisby.org
License: GPL
Keywords: corba
Platform: any
Classifier: Development Status :: 5 - Production/Stable
Classifier: License :: OSI Approved :: GNU General Public License v3 or later (GPLv3+)
Classifier: Programming Language :: C++
Classifier: Programming Language :: Python :: 3
Classifier: Topic :: Scientific/Engineering :: Physics
Classifier: Intended Audience :: Science/Research
